procaine/__init__.py
procaine/aicore.py
procaine-0.4.1.dist-info/LICENSE.txt
procaine-0.4.1.dist-info/WHEEL
procaine-0.4.1.dist-info/METADATA
procaine-0.4.1.dist-info/RECORD
