Metadata-Version: 2.1
Name: procaine
Version: 0.4.1
Summary: A REST client library for SAP AI Core API.
Keywords: AI Core,AICore,AI API,ai-api
Author: romk
Requires-Python: >=3.7
Classifier: Development Status :: 4 - Beta
Classifier: Intended Audience :: Developers
Classifier: Natural Language :: English
Classifier: Programming Language :: Python
Classifier: Programming Language :: Python :: 3
Classifier: Programming Language :: Python :: 3.7
Classifier: Programming Language :: Python :: 3.8
Classifier: Programming Language :: Python :: 3.9
Classifier: Programming Language :: Python :: 3.10
Classifier: Programming Language :: Python :: 3 :: Only
Classifier: License :: OSI Approved :: GNU General Public License v2 or later (GPLv2+)
Classifier: Operating System :: MacOS :: MacOS X
Classifier: Operating System :: POSIX :: Linux
Classifier: Topic :: Internet :: WWW/HTTP
Classifier: Topic :: Software Development :: Libraries
Classifier: Topic :: Scientific/Engineering :: Artificial Intelligence
Requires-Dist: requests
Requires-Dist: authlib
Project-URL: Documentation, https://procaine.readthedocs.io
Project-URL: Homepage, https://procaine.readthedocs.io
Project-URL: Issues, https://gitlab.com/romk/procaine/-/issues
Project-URL: Repository, https://gitlab.com/romk/procaine
